{
  "count": 946,
  "uniques": 341,
  "clones": [
    {
      "timestamp": "2022-02-20T00:00:00Z",
      "count": 79,
      "uniques": 29
    },
    {
      "timestamp": "2022-02-21T00:00:00Z",
      "count": 79,
      "uniques": 29
    },
    {
      "timestamp": "2022-02-22T00:00:00Z",
      "count": 79,
      "uniques": 29
    },
    {
      "timestamp": "2022-02-23T00:00:00Z",
      "count": 73,
      "uniques": 28
    },
    {
      "timestamp": "2022-02-24T00:00:00Z",
      "count": 71,
      "uniques": 25
    },
    {
      "timestamp": "2022-02-25T00:00:00Z",
      "count": 70,
      "uniques": 25
    },
    {
      "timestamp": "2022-02-26T00:00:00Z",
      "count": 70,
      "uniques": 25
    },
    {
      "timestamp": "2022-02-27T00:00:00Z",
      "count": 72,
      "uniques": 26
    },
    {
      "timestamp": "2022-02-28T00:00:00Z",
      "count": 71,
      "uniques": 25
    },
    {
      "timestamp": "2022-03-01T00:00:00Z",
      "count": 71,
      "uniques": 25
    },
    {
      "timestamp": "2022-03-02T00:00:00Z",
      "count": 71,
      "uniques": 25
    },
    {
      "timestamp": "2022-03-03T00:00:00Z",
      "count": 70,
      "uniques": 25
    },
    {
      "timestamp": "2022-03-04T00:00:00Z",
      "count": 70,
      "uniques": 25
    }
  ]
}