{
  "count": 1366,
  "uniques": 470,
  "clones": [
    {
      "timestamp": "2021-11-14T00:00:00Z",
      "count": 238,
      "uniques": 81
    },
    {
      "timestamp": "2021-11-15T00:00:00Z",
      "count": 233,
      "uniques": 79
    },
    {
      "timestamp": "2021-11-16T00:00:00Z",
      "count": 239,
      "uniques": 82
    },
    {
      "timestamp": "2021-11-17T00:00:00Z",
      "count": 238,
      "uniques": 83
    },
    {
      "timestamp": "2021-11-18T00:00:00Z",
      "count": 232,
      "uniques": 79
    },
    {
      "timestamp": "2021-11-19T00:00:00Z",
      "count": 112,
      "uniques": 40
    },
    {
      "timestamp": "2021-11-20T00:00:00Z",
      "count": 74,
      "uniques": 26
    }
  ]
}