[
  {
    "referrer": "Google",
    "count": 144,
    "uniques": 75
  },
  {
    "referrer": "github.com",
    "count": 71,
    "uniques": 26
  },
  {
    "referrer": "reddit.com",
    "count": 34,
    "uniques": 9
  },
  {
    "referrer": "joinup.ec.europa.eu",
    "count": 8,
    "uniques": 3
  },
  {
    "referrer": "Bing",
    "count": 5,
    "uniques": 2
  },
  {
    "referrer": "DuckDuckGo",
    "count": 3,
    "uniques": 2
  },
  {
    "referrer": "statics.teams.cdn.office.net",
    "count": 2,
    "uniques": 2
  },
  {
    "referrer": "com.linkedin.android",
    "count": 1,
    "uniques": 1
  }
]