[
  {
    "referrer": "reddit.com",
    "count": 30,
    "uniques": 27
  },
  {
    "referrer": "linkedin.com",
    "count": 23,
    "uniques": 22
  },
  {
    "referrer": "Google",
    "count": 14,
    "uniques": 13
  },
  {
    "referrer": "github.com",
    "count": 13,
    "uniques": 10
  },
  {
    "referrer": "out.reddit.com",
    "count": 9,
    "uniques": 3
  },
  {
    "referrer": "joinup.ec.europa.eu",
    "count": 6,
    "uniques": 3
  },
  {
    "referrer": "lnkd.in",
    "count": 3,
    "uniques": 3
  },
  {
    "referrer": "Bing",
    "count": 2,
    "uniques": 2
  },
  {
    "referrer": "account.activedirectory.windowsazure.com",
    "count": 2,
    "uniques": 2
  },
  {
    "referrer": "cn.bing.com",
    "count": 1,
    "uniques": 1
  }
]